little_finger/__init__.py
little_finger/cache/__init__.py
little_finger/cache/redis_client.py
little_finger/compare_data/__init__.py
little_finger/compare_data/compare_data_raw.py
little_finger/compare_data/compare_excel_column.py
little_finger/img/__init__.py
little_finger/img/smms.py
little_finger/log_reader/__init__.py
little_finger/log_reader/log_reader.py
little_finger/log_reader/log_reader_v2.py
little_finger/logg/__init__.py
little_finger/logg/logg.py
little_finger/logg/mongo_logg.py
little_finger/notify/__init__.py
little_finger/notify/email_client.py
little_finger/notify/ifttt_client.py
little_finger/notify/wecom_cache_client.py
little_finger/notify/wecom_client.py
little_finger/router/__init__.py
little_finger/router/router.py
little_finger/router/signal.py
little_finger/utils/__init__.py
little_finger/utils/data_util.py
little_finger/utils/date_util.py
little_finger/utils/file_util.py
little_finger/utils/json_util.py
little_finger/utils/list_util.py
little_finger/utils/requests_response_util.py
little_finger/utils/requests_util.py
little_finger-0.0.19.dist-info/LICENSE
little_finger-0.0.19.dist-info/METADATA
little_finger-0.0.19.dist-info/WHEEL
little_finger-0.0.19.dist-info/top_level.txt
little_finger-0.0.19.dist-info/RECORD
